c3/__init__.py
c3/billing.py
c3/client.py
c3/config.py
c3/files.py
c3/http.py
c3/instances.py
c3/jobs.py
c3/logs.py
c3/renders.py
c3/user.py
c3/job/__init__.py
c3/job/base.py
c3/job/comfyui.py
c3_sdk-0.4.2.dist-info/METADATA
c3_sdk-0.4.2.dist-info/WHEEL
c3_sdk-0.4.2.dist-info/RECORD
