Metadata-Version: 2.4
Name: c3-sdk
Version: 0.4.2
Summary: Python SDK for Compute3 - GPU orchestration and LLM API
Project-URL: Homepage, https://compute3.ai
Project-URL: Documentation, https://docs.compute3.ai
Project-URL: Repository, https://github.com/compute3/sdk-python
Author-email: Compute3 <support@compute3.ai>
License-Expression: MIT
Classifier: Development Status :: 4 - Beta
Classifier: Intended Audience :: Developers
Classifier: License :: OSI Approved :: MIT License
Classifier: Programming Language :: Python :: 3.10
Classifier: Programming Language :: Python :: 3.11
Classifier: Programming Language :: Python :: 3.12
Requires-Python: >=3.10
Requires-Dist: httpx>=0.28.1
Requires-Dist: websockets>=15.0.1
Provides-Extra: comfyui
Requires-Dist: comfyui-workflow-templates-media-image>=0.3.0; extra == 'comfyui'
Requires-Dist: comfyui-workflow-templates>=0.7.0; extra == 'comfyui'
Provides-Extra: dev
Requires-Dist: pytest-asyncio>=0.23.0; extra == 'dev'
Requires-Dist: pytest>=8.0.0; extra == 'dev'
Requires-Dist: ruff>=0.3.0; extra == 'dev'
